ansys/engineeringworkflow/api/__init__.py
ansys/engineeringworkflow/api/datatypes.py
ansys/engineeringworkflow/api/exceptions.py
ansys/engineeringworkflow/api/iasyncworkflow.py
ansys/engineeringworkflow/api/iworkflow.py
ansys/engineeringworkflow/api/py.typed
ansys_engineeringworkflow_api-0.1.2.dist-info/licenses/LICENSE
ansys_engineeringworkflow_api-0.1.2.dist-info/WHEEL
ansys_engineeringworkflow_api-0.1.2.dist-info/METADATA
ansys_engineeringworkflow_api-0.1.2.dist-info/RECORD
