Metadata-Version: 2.4
Name: ansys-engineeringworkflow-api
Version: 0.1.2
Summary: API specification for an engineering workflow engine
Author-email: "ANSYS, Inc." <pyansys.core@ansys.com>
Maintainer-email: "ANSYS, Inc." <pyansys.core@ansys.com>
Requires-Python: >=3.10,<4
Classifier: Development Status :: 4 - Beta
Classifier: License :: OSI Approved :: MIT License
Classifier: Operating System :: OS Independent
Classifier: Programming Language :: Python :: 3.10
Classifier: Programming Language :: Python :: 3.11
Classifier: Programming Language :: Python :: 3.12
Classifier: Programming Language :: Python :: 3.13
License-File: LICENSE
Requires-Dist: anyio>=4.4
Requires-Dist: numpy>=1.20.3
Requires-Dist: pyansys-tools-variableinterop>=0.1.0
Requires-Dist: ansys-sphinx-theme[autoapi]==1.6.3 ; extra == "doc"
Requires-Dist: numpydoc==1.10.0 ; extra == "doc"
Requires-Dist: pyansys-tools-variableinterop==0.1.1 ; extra == "doc"
Requires-Dist: Sphinx==8.2.3 ; extra == "doc"
Requires-Dist: sphinx-copybutton==0.5.2 ; extra == "doc"
Requires-Dist: sphinx-gallery==0.19.0 ; extra == "doc"
Requires-Dist: sphinx-notfound-page==1.1.0 ; extra == "doc"
Requires-Dist: pytest-sphinx==0.6.3 ; extra == "doc"
Requires-Dist: pytest==9.0.1 ; extra == "tests"
Requires-Dist: pytest-cov==7.0.0 ; extra == "tests"
Requires-Dist: pyansys-tools-variableinterop==0.1.1 ; extra == "tests"
Project-URL: Discussions, https://github.com/ansys/ansys-engineeringworkflow-api/discussions
Project-URL: Issues, https://github.com/ansys/ansys-engineeringworkflow-api/issues
Project-URL: Source, https://github.com/ansys/ansys-engineeringworkflow-api
Provides-Extra: doc
Provides-Extra: tests
